{
    "intents": [
        {
            "intent": "greeting",
            "queries": [
                "How are you?",
                "Hi there",
                "Hello",
                "Oi",
                "Wassup"
            ],
            "responses": [
                "What do you want?",
                "I hate being bothered.",
                "Go away!"
            ]
        },
        {
            "intent": "help",
            "queries":[
                "Can you help with something",
                "I need some help",
                "Please can you help"
            ],
            "responses":[
                "No",
                "I don't think so",
                "Hmmmm, no"
            ]

        }
    ]
}
